[
  {
    "Query": {
      "Name": "foo.foo.uni.bankcard.",
      "Type": "A"
    },
    "Expected Response": [
      {
        "Server/s": "bind nsd knot powerdns ",
        "Response": [
          "id 29949",
          "opcode QUERY",
          "rcode NOERROR",
          "flags QR",
          ";QUESTION",
          "foo.foo.uni.bankcard. IN A",
          ";ANSWER",
          ";AUTHORITY",
          "foo.foo.uni.bankcard. 500 IN NS *.campus.bankcard.bankcard.",
          "foo.foo.uni.bankcard. 500 IN NS foo.fnni.bankcard.",
          ";ADDITIONAL"
        ]
      }
    ],
    "ZenResponseTag": "E4"
  }
]