[
  {
    "Query": {
      "Name": "email.com.",
      "Type": "DNAME"
    },
    "Expected Response": [
      {
        "Server/s": "bind nsd knot powerdns ",
        "Response": [
          "id 44322",
          "opcode QUERY",
          "rcode NOERROR",
          "flags QR AA",
          ";QUESTION",
          "email.com. IN DNAME",
          ";ANSWER",
          "email.com. 500 IN DNAME com.",
          ";AUTHORITY",
          "email.com. 500 IN NS com.mybankcard.www.",
          ";ADDITIONAL"
        ]
      }
    ],
    "ZenResponseTag": "E1"
  }
]