[
  {
    "Query": {
      "Name": "net.example.campus.bankcard.",
      "Type": "A"
    },
    "Expected Response": [
      {
        "Server/s": "bind nsd ",
        "Response": [
          "id 12413",
          "opcode QUERY",
          "rcode NOERROR",
          "flags QR",
          ";QUESTION",
          "net.example.campus.bankcard. IN A",
          ";ANSWER",
          ";AUTHORITY",
          "net.example.campus.bankcard. 500 IN NS uni.campus.bar.example.",
          ";ADDITIONAL"
        ]
      }
    ]
  },
  {
    "Query": {
      "Name": "net.example.campus.bankcard.",
      "Type": "NS"
    },
    "Expected Response": [
      {
        "Server/s": "bind nsd ",
        "Response": [
          "id 49200",
          "opcode QUERY",
          "rcode NOERROR",
          "flags QR",
          ";QUESTION",
          "net.example.campus.bankcard. IN NS",
          ";ANSWER",
          ";AUTHORITY",
          "net.example.campus.bankcard. 500 IN NS uni.campus.bar.example.",
          ";ADDITIONAL"
        ]
      }
    ]
  },
  {
    "Query": {
      "Name": "net.example.campus.bankcard.",
      "Type": "SOA"
    },
    "Expected Response": [
      {
        "Server/s": "bind nsd ",
        "Response": [
          "id 61646",
          "opcode QUERY",
          "rcode NOERROR",
          "flags QR",
          ";QUESTION",
          "net.example.campus.bankcard. IN SOA",
          ";ANSWER",
          ";AUTHORITY",
          "net.example.campus.bankcard. 500 IN NS uni.campus.bar.example.",
          ";ADDITIONAL"
        ]
      }
    ]
  },
  {
    "Query": {
      "Name": "net.example.campus.bankcard.",
      "Type": "CNAME"
    },
    "Expected Response": [
      {
        "Server/s": "bind nsd ",
        "Response": [
          "id 14422",
          "opcode QUERY",
          "rcode NOERROR",
          "flags QR",
          ";QUESTION",
          "net.example.campus.bankcard. IN CNAME",
          ";ANSWER",
          ";AUTHORITY",
          "net.example.campus.bankcard. 500 IN NS uni.campus.bar.example.",
          ";ADDITIONAL"
        ]
      }
    ]
  },
  {
    "Query": {
      "Name": "net.example.campus.bankcard.",
      "Type": "DNAME"
    },
    "Expected Response": [
      {
        "Server/s": "bind nsd ",
        "Response": [
          "id 47425",
          "opcode QUERY",
          "rcode NOERROR",
          "flags QR",
          ";QUESTION",
          "net.example.campus.bankcard. IN DNAME",
          ";ANSWER",
          ";AUTHORITY",
          "net.example.campus.bankcard. 500 IN NS uni.campus.bar.example.",
          ";ADDITIONAL"
        ]
      }
    ]
  },
  {
    "Query": {
      "Name": "net.example.campus.bankcard.",
      "Type": "TXT"
    },
    "Expected Response": [
      {
        "Server/s": "bind nsd ",
        "Response": [
          "id 12643",
          "opcode QUERY",
          "rcode NOERROR",
          "flags QR",
          ";QUESTION",
          "net.example.campus.bankcard. IN TXT",
          ";ANSWER",
          ";AUTHORITY",
          "net.example.campus.bankcard. 500 IN NS uni.campus.bar.example.",
          ";ADDITIONAL"
        ]
      }
    ]
  },
  {
    "Query": {
      "Name": "a.net.example.campus.bankcard.",
      "Type": "A"
    },
    "Expected Response": [
      {
        "Server/s": "bind nsd ",
        "Response": [
          "id 41294",
          "opcode QUERY",
          "rcode NOERROR",
          "flags QR",
          ";QUESTION",
          "a.net.example.campus.bankcard. IN A",
          ";ANSWER",
          ";AUTHORITY",
          "net.example.campus.bankcard. 500 IN NS uni.campus.bar.example.",
          ";ADDITIONAL"
        ]
      }
    ]
  },
  {
    "Query": {
      "Name": "a.net.example.campus.bankcard.",
      "Type": "NS"
    },
    "Expected Response": [
      {
        "Server/s": "bind nsd ",
        "Response": [
          "id 53670",
          "opcode QUERY",
          "rcode NOERROR",
          "flags QR",
          ";QUESTION",
          "a.net.example.campus.bankcard. IN NS",
          ";ANSWER",
          ";AUTHORITY",
          "net.example.campus.bankcard. 500 IN NS uni.campus.bar.example.",
          ";ADDITIONAL"
        ]
      }
    ]
  },
  {
    "Query": {
      "Name": "a.net.example.campus.bankcard.",
      "Type": "SOA"
    },
    "Expected Response": [
      {
        "Server/s": "bind nsd ",
        "Response": [
          "id 29061",
          "opcode QUERY",
          "rcode NOERROR",
          "flags QR",
          ";QUESTION",
          "a.net.example.campus.bankcard. IN SOA",
          ";ANSWER",
          ";AUTHORITY",
          "net.example.campus.bankcard. 500 IN NS uni.campus.bar.example.",
          ";ADDITIONAL"
        ]
      }
    ]
  },
  {
    "Query": {
      "Name": "a.net.example.campus.bankcard.",
      "Type": "CNAME"
    },
    "Expected Response": [
      {
        "Server/s": "bind nsd ",
        "Response": [
          "id 15466",
          "opcode QUERY",
          "rcode NOERROR",
          "flags QR",
          ";QUESTION",
          "a.net.example.campus.bankcard. IN CNAME",
          ";ANSWER",
          ";AUTHORITY",
          "net.example.campus.bankcard. 500 IN NS uni.campus.bar.example.",
          ";ADDITIONAL"
        ]
      }
    ]
  },
  {
    "Query": {
      "Name": "a.net.example.campus.bankcard.",
      "Type": "DNAME"
    },
    "Expected Response": [
      {
        "Server/s": "bind nsd ",
        "Response": [
          "id 40458",
          "opcode QUERY",
          "rcode NOERROR",
          "flags QR",
          ";QUESTION",
          "a.net.example.campus.bankcard. IN DNAME",
          ";ANSWER",
          ";AUTHORITY",
          "net.example.campus.bankcard. 500 IN NS uni.campus.bar.example.",
          ";ADDITIONAL"
        ]
      }
    ]
  },
  {
    "Query": {
      "Name": "a.net.example.campus.bankcard.",
      "Type": "TXT"
    },
    "Expected Response": [
      {
        "Server/s": "bind nsd ",
        "Response": [
          "id 21346",
          "opcode QUERY",
          "rcode NOERROR",
          "flags QR",
          ";QUESTION",
          "a.net.example.campus.bankcard. IN TXT",
          ";ANSWER",
          ";AUTHORITY",
          "net.example.campus.bankcard. 500 IN NS uni.campus.bar.example.",
          ";ADDITIONAL"
        ]
      }
    ]
  },
  {
    "Query": {
      "Name": "example.campus.bankcard.",
      "Type": "A"
    },
    "Expected Response": [
      {
        "Server/s": "bind nsd ",
        "Response": [
          "id 47258",
          "opcode QUERY",
          "rcode NOERROR",
          "flags QR AA",
          ";QUESTION",
          "example.campus.bankcard. IN A",
          ";ANSWER",
          ";AUTHORITY",
          "bankcard. 500 IN SOA ns1.outside.edu. root.campus.edu. 3 6048 86400 2419200 6048",
          ";ADDITIONAL"
        ]
      }
    ]
  },
  {
    "Query": {
      "Name": "example.campus.bankcard.",
      "Type": "NS"
    },
    "Expected Response": [
      {
        "Server/s": "bind nsd ",
        "Response": [
          "id 47113",
          "opcode QUERY",
          "rcode NOERROR",
          "flags QR AA",
          ";QUESTION",
          "example.campus.bankcard. IN NS",
          ";ANSWER",
          ";AUTHORITY",
          "bankcard. 500 IN SOA ns1.outside.edu. root.campus.edu. 3 6048 86400 2419200 6048",
          ";ADDITIONAL"
        ]
      }
    ]
  },
  {
    "Query": {
      "Name": "example.campus.bankcard.",
      "Type": "SOA"
    },
    "Expected Response": [
      {
        "Server/s": "bind nsd ",
        "Response": [
          "id 54919",
          "opcode QUERY",
          "rcode NOERROR",
          "flags QR AA",
          ";QUESTION",
          "example.campus.bankcard. IN SOA",
          ";ANSWER",
          ";AUTHORITY",
          "bankcard. 500 IN SOA ns1.outside.edu. root.campus.edu. 3 6048 86400 2419200 6048",
          ";ADDITIONAL"
        ]
      }
    ]
  },
  {
    "Query": {
      "Name": "example.campus.bankcard.",
      "Type": "CNAME"
    },
    "Expected Response": [
      {
        "Server/s": "bind nsd ",
        "Response": [
          "id 19181",
          "opcode QUERY",
          "rcode NOERROR",
          "flags QR AA",
          ";QUESTION",
          "example.campus.bankcard. IN CNAME",
          ";ANSWER",
          ";AUTHORITY",
          "bankcard. 500 IN SOA ns1.outside.edu. root.campus.edu. 3 6048 86400 2419200 6048",
          ";ADDITIONAL"
        ]
      }
    ]
  },
  {
    "Query": {
      "Name": "example.campus.bankcard.",
      "Type": "DNAME"
    },
    "Expected Response": [
      {
        "Server/s": "bind nsd ",
        "Response": [
          "id 4815",
          "opcode QUERY",
          "rcode NOERROR",
          "flags QR AA",
          ";QUESTION",
          "example.campus.bankcard. IN DNAME",
          ";ANSWER",
          ";AUTHORITY",
          "bankcard. 500 IN SOA ns1.outside.edu. root.campus.edu. 3 6048 86400 2419200 6048",
          ";ADDITIONAL"
        ]
      }
    ]
  },
  {
    "Query": {
      "Name": "example.campus.bankcard.",
      "Type": "TXT"
    },
    "Expected Response": [
      {
        "Server/s": "bind nsd ",
        "Response": [
          "id 40611",
          "opcode QUERY",
          "rcode NOERROR",
          "flags QR AA",
          ";QUESTION",
          "example.campus.bankcard. IN TXT",
          ";ANSWER",
          ";AUTHORITY",
          "bankcard. 500 IN SOA ns1.outside.edu. root.campus.edu. 3 6048 86400 2419200 6048",
          ";ADDITIONAL"
        ]
      }
    ]
  },
  {
    "Query": {
      "Name": "a.example.campus.bankcard.",
      "Type": "A"
    },
    "Expected Response": [
      {
        "Server/s": "bind nsd ",
        "Response": [
          "id 37299",
          "opcode QUERY",
          "rcode NXDOMAIN",
          "flags QR AA",
          ";QUESTION",
          "a.example.campus.bankcard. IN A",
          ";ANSWER",
          ";AUTHORITY",
          "bankcard. 500 IN SOA ns1.outside.edu. root.campus.edu. 3 6048 86400 2419200 6048",
          ";ADDITIONAL"
        ]
      }
    ]
  },
  {
    "Query": {
      "Name": "a.example.campus.bankcard.",
      "Type": "NS"
    },
    "Expected Response": [
      {
        "Server/s": "bind nsd ",
        "Response": [
          "id 22050",
          "opcode QUERY",
          "rcode NXDOMAIN",
          "flags QR AA",
          ";QUESTION",
          "a.example.campus.bankcard. IN NS",
          ";ANSWER",
          ";AUTHORITY",
          "bankcard. 500 IN SOA ns1.outside.edu. root.campus.edu. 3 6048 86400 2419200 6048",
          ";ADDITIONAL"
        ]
      }
    ]
  },
  {
    "Query": {
      "Name": "a.example.campus.bankcard.",
      "Type": "SOA"
    },
    "Expected Response": [
      {
        "Server/s": "bind nsd ",
        "Response": [
          "id 8635",
          "opcode QUERY",
          "rcode NXDOMAIN",
          "flags QR AA",
          ";QUESTION",
          "a.example.campus.bankcard. IN SOA",
          ";ANSWER",
          ";AUTHORITY",
          "bankcard. 0 IN SOA ns1.outside.edu. root.campus.edu. 3 6048 86400 2419200 6048",
          ";ADDITIONAL"
        ]
      }
    ]
  },
  {
    "Query": {
      "Name": "a.example.campus.bankcard.",
      "Type": "CNAME"
    },
    "Expected Response": [
      {
        "Server/s": "bind nsd ",
        "Response": [
          "id 16946",
          "opcode QUERY",
          "rcode NXDOMAIN",
          "flags QR AA",
          ";QUESTION",
          "a.example.campus.bankcard. IN CNAME",
          ";ANSWER",
          ";AUTHORITY",
          "bankcard. 500 IN SOA ns1.outside.edu. root.campus.edu. 3 6048 86400 2419200 6048",
          ";ADDITIONAL"
        ]
      }
    ]
  },
  {
    "Query": {
      "Name": "a.example.campus.bankcard.",
      "Type": "DNAME"
    },
    "Expected Response": [
      {
        "Server/s": "bind nsd ",
        "Response": [
          "id 62507",
          "opcode QUERY",
          "rcode NXDOMAIN",
          "flags QR AA",
          ";QUESTION",
          "a.example.campus.bankcard. IN DNAME",
          ";ANSWER",
          ";AUTHORITY",
          "bankcard. 500 IN SOA ns1.outside.edu. root.campus.edu. 3 6048 86400 2419200 6048",
          ";ADDITIONAL"
        ]
      }
    ]
  },
  {
    "Query": {
      "Name": "a.example.campus.bankcard.",
      "Type": "TXT"
    },
    "Expected Response": [
      {
        "Server/s": "bind nsd ",
        "Response": [
          "id 19355",
          "opcode QUERY",
          "rcode NXDOMAIN",
          "flags QR AA",
          ";QUESTION",
          "a.example.campus.bankcard. IN TXT",
          ";ANSWER",
          ";AUTHORITY",
          "bankcard. 500 IN SOA ns1.outside.edu. root.campus.edu. 3 6048 86400 2419200 6048",
          ";ADDITIONAL"
        ]
      }
    ]
  },
  {
    "Query": {
      "Name": "campus.bankcard.",
      "Type": "A"
    },
    "Expected Response": [
      {
        "Server/s": "bind nsd ",
        "Response": [
          "id 6031",
          "opcode QUERY",
          "rcode NOERROR",
          "flags QR AA",
          ";QUESTION",
          "campus.bankcard. IN A",
          ";ANSWER",
          ";AUTHORITY",
          "bankcard. 500 IN SOA ns1.outside.edu. root.campus.edu. 3 6048 86400 2419200 6048",
          ";ADDITIONAL"
        ]
      }
    ]
  },
  {
    "Query": {
      "Name": "campus.bankcard.",
      "Type": "NS"
    },
    "Expected Response": [
      {
        "Server/s": "bind nsd ",
        "Response": [
          "id 45934",
          "opcode QUERY",
          "rcode NOERROR",
          "flags QR AA",
          ";QUESTION",
          "campus.bankcard. IN NS",
          ";ANSWER",
          ";AUTHORITY",
          "bankcard. 500 IN SOA ns1.outside.edu. root.campus.edu. 3 6048 86400 2419200 6048",
          ";ADDITIONAL"
        ]
      }
    ]
  },
  {
    "Query": {
      "Name": "campus.bankcard.",
      "Type": "SOA"
    },
    "Expected Response": [
      {
        "Server/s": "bind nsd ",
        "Response": [
          "id 40046",
          "opcode QUERY",
          "rcode NOERROR",
          "flags QR AA",
          ";QUESTION",
          "campus.bankcard. IN SOA",
          ";ANSWER",
          ";AUTHORITY",
          "bankcard. 500 IN SOA ns1.outside.edu. root.campus.edu. 3 6048 86400 2419200 6048",
          ";ADDITIONAL"
        ]
      }
    ]
  },
  {
    "Query": {
      "Name": "campus.bankcard.",
      "Type": "CNAME"
    },
    "Expected Response": [
      {
        "Server/s": "bind nsd ",
        "Response": [
          "id 27531",
          "opcode QUERY",
          "rcode NOERROR",
          "flags QR AA",
          ";QUESTION",
          "campus.bankcard. IN CNAME",
          ";ANSWER",
          ";AUTHORITY",
          "bankcard. 500 IN SOA ns1.outside.edu. root.campus.edu. 3 6048 86400 2419200 6048",
          ";ADDITIONAL"
        ]
      }
    ]
  },
  {
    "Query": {
      "Name": "campus.bankcard.",
      "Type": "DNAME"
    },
    "Expected Response": [
      {
        "Server/s": "bind nsd ",
        "Response": [
          "id 36939",
          "opcode QUERY",
          "rcode NOERROR",
          "flags QR AA",
          ";QUESTION",
          "campus.bankcard. IN DNAME",
          ";ANSWER",
          ";AUTHORITY",
          "bankcard. 500 IN SOA ns1.outside.edu. root.campus.edu. 3 6048 86400 2419200 6048",
          ";ADDITIONAL"
        ]
      }
    ]
  },
  {
    "Query": {
      "Name": "campus.bankcard.",
      "Type": "TXT"
    },
    "Expected Response": [
      {
        "Server/s": "bind nsd ",
        "Response": [
          "id 54633",
          "opcode QUERY",
          "rcode NOERROR",
          "flags QR AA",
          ";QUESTION",
          "campus.bankcard. IN TXT",
          ";ANSWER",
          ";AUTHORITY",
          "bankcard. 500 IN SOA ns1.outside.edu. root.campus.edu. 3 6048 86400 2419200 6048",
          ";ADDITIONAL"
        ]
      }
    ]
  },
  {
    "Query": {
      "Name": "a.campus.bankcard.",
      "Type": "A"
    },
    "Expected Response": [
      {
        "Server/s": "bind nsd ",
        "Response": [
          "id 51275",
          "opcode QUERY",
          "rcode NXDOMAIN",
          "flags QR AA",
          ";QUESTION",
          "a.campus.bankcard. IN A",
          ";ANSWER",
          ";AUTHORITY",
          "bankcard. 500 IN SOA ns1.outside.edu. root.campus.edu. 3 6048 86400 2419200 6048",
          ";ADDITIONAL"
        ]
      }
    ]
  },
  {
    "Query": {
      "Name": "a.campus.bankcard.",
      "Type": "NS"
    },
    "Expected Response": [
      {
        "Server/s": "bind nsd ",
        "Response": [
          "id 39873",
          "opcode QUERY",
          "rcode NXDOMAIN",
          "flags QR AA",
          ";QUESTION",
          "a.campus.bankcard. IN NS",
          ";ANSWER",
          ";AUTHORITY",
          "bankcard. 500 IN SOA ns1.outside.edu. root.campus.edu. 3 6048 86400 2419200 6048",
          ";ADDITIONAL"
        ]
      }
    ]
  },
  {
    "Query": {
      "Name": "a.campus.bankcard.",
      "Type": "SOA"
    },
    "Expected Response": [
      {
        "Server/s": "bind nsd ",
        "Response": [
          "id 50254",
          "opcode QUERY",
          "rcode NXDOMAIN",
          "flags QR AA",
          ";QUESTION",
          "a.campus.bankcard. IN SOA",
          ";ANSWER",
          ";AUTHORITY",
          "bankcard. 0 IN SOA ns1.outside.edu. root.campus.edu. 3 6048 86400 2419200 6048",
          ";ADDITIONAL"
        ]
      }
    ]
  },
  {
    "Query": {
      "Name": "a.campus.bankcard.",
      "Type": "CNAME"
    },
    "Expected Response": [
      {
        "Server/s": "bind nsd ",
        "Response": [
          "id 19339",
          "opcode QUERY",
          "rcode NXDOMAIN",
          "flags QR AA",
          ";QUESTION",
          "a.campus.bankcard. IN CNAME",
          ";ANSWER",
          ";AUTHORITY",
          "bankcard. 500 IN SOA ns1.outside.edu. root.campus.edu. 3 6048 86400 2419200 6048",
          ";ADDITIONAL"
        ]
      }
    ]
  },
  {
    "Query": {
      "Name": "a.campus.bankcard.",
      "Type": "DNAME"
    },
    "Expected Response": [
      {
        "Server/s": "bind nsd ",
        "Response": [
          "id 42386",
          "opcode QUERY",
          "rcode NXDOMAIN",
          "flags QR AA",
          ";QUESTION",
          "a.campus.bankcard. IN DNAME",
          ";ANSWER",
          ";AUTHORITY",
          "bankcard. 500 IN SOA ns1.outside.edu. root.campus.edu. 3 6048 86400 2419200 6048",
          ";ADDITIONAL"
        ]
      }
    ]
  },
  {
    "Query": {
      "Name": "a.campus.bankcard.",
      "Type": "TXT"
    },
    "Expected Response": [
      {
        "Server/s": "bind nsd ",
        "Response": [
          "id 24714",
          "opcode QUERY",
          "rcode NXDOMAIN",
          "flags QR AA",
          ";QUESTION",
          "a.campus.bankcard. IN TXT",
          ";ANSWER",
          ";AUTHORITY",
          "bankcard. 500 IN SOA ns1.outside.edu. root.campus.edu. 3 6048 86400 2419200 6048",
          ";ADDITIONAL"
        ]
      }
    ]
  },
  {
    "Query": {
      "Name": "example.bankcard.",
      "Type": "A"
    },
    "Expected Response": [
      {
        "Server/s": "bind nsd ",
        "Response": [
          "id 23149",
          "opcode QUERY",
          "rcode NOERROR",
          "flags QR AA",
          ";QUESTION",
          "example.bankcard. IN A",
          ";ANSWER",
          ";AUTHORITY",
          "bankcard. 500 IN SOA ns1.outside.edu. root.campus.edu. 3 6048 86400 2419200 6048",
          ";ADDITIONAL"
        ]
      }
    ]
  },
  {
    "Query": {
      "Name": "example.bankcard.",
      "Type": "NS"
    },
    "Expected Response": [
      {
        "Server/s": "bind nsd ",
        "Response": [
          "id 1344",
          "opcode QUERY",
          "rcode NOERROR",
          "flags QR AA",
          ";QUESTION",
          "example.bankcard. IN NS",
          ";ANSWER",
          ";AUTHORITY",
          "bankcard. 500 IN SOA ns1.outside.edu. root.campus.edu. 3 6048 86400 2419200 6048",
          ";ADDITIONAL"
        ]
      }
    ]
  },
  {
    "Query": {
      "Name": "example.bankcard.",
      "Type": "SOA"
    },
    "Expected Response": [
      {
        "Server/s": "bind nsd ",
        "Response": [
          "id 18789",
          "opcode QUERY",
          "rcode NOERROR",
          "flags QR AA",
          ";QUESTION",
          "example.bankcard. IN SOA",
          ";ANSWER",
          ";AUTHORITY",
          "bankcard. 500 IN SOA ns1.outside.edu. root.campus.edu. 3 6048 86400 2419200 6048",
          ";ADDITIONAL"
        ]
      }
    ]
  },
  {
    "Query": {
      "Name": "example.bankcard.",
      "Type": "CNAME"
    },
    "Expected Response": [
      {
        "Server/s": "bind nsd ",
        "Response": [
          "id 47069",
          "opcode QUERY",
          "rcode NOERROR",
          "flags QR AA",
          ";QUESTION",
          "example.bankcard. IN CNAME",
          ";ANSWER",
          ";AUTHORITY",
          "bankcard. 500 IN SOA ns1.outside.edu. root.campus.edu. 3 6048 86400 2419200 6048",
          ";ADDITIONAL"
        ]
      }
    ]
  },
  {
    "Query": {
      "Name": "example.bankcard.",
      "Type": "DNAME"
    },
    "Expected Response": [
      {
        "Server/s": "bind nsd ",
        "Response": [
          "id 38944",
          "opcode QUERY",
          "rcode NOERROR",
          "flags QR AA",
          ";QUESTION",
          "example.bankcard. IN DNAME",
          ";ANSWER",
          "example.bankcard. 500 IN DNAME example.bankcard.",
          ";AUTHORITY",
          "bankcard. 500 IN NS ns1.outside.edu.",
          ";ADDITIONAL"
        ]
      }
    ]
  },
  {
    "Query": {
      "Name": "example.bankcard.",
      "Type": "TXT"
    },
    "Expected Response": [
      {
        "Server/s": "bind nsd ",
        "Response": [
          "id 24588",
          "opcode QUERY",
          "rcode NOERROR",
          "flags QR AA",
          ";QUESTION",
          "example.bankcard. IN TXT",
          ";ANSWER",
          ";AUTHORITY",
          "bankcard. 500 IN SOA ns1.outside.edu. root.campus.edu. 3 6048 86400 2419200 6048",
          ";ADDITIONAL"
        ]
      }
    ]
  },
  {
    "Query": {
      "Name": "a.example.bankcard.",
      "Type": "A"
    },
    "Expected Response": [
      {
        "Server/s": "bind nsd ",
        "Response": [
          "id 36271",
          "opcode QUERY",
          "rcode NOERROR",
          "flags QR AA",
          ";QUESTION",
          "a.example.bankcard. IN A",
          ";ANSWER",
          "example.bankcard. 500 IN DNAME example.bankcard.",
          "a.example.bankcard. 500 IN CNAME a.example.bankcard.",
          ";AUTHORITY",
          ";ADDITIONAL"
        ]
      }
    ]
  },
  {
    "Query": {
      "Name": "a.example.bankcard.",
      "Type": "NS"
    },
    "Expected Response": [
      {
        "Server/s": "bind nsd ",
        "Response": [
          "id 43853",
          "opcode QUERY",
          "rcode NOERROR",
          "flags QR AA",
          ";QUESTION",
          "a.example.bankcard. IN NS",
          ";ANSWER",
          "example.bankcard. 500 IN DNAME example.bankcard.",
          "a.example.bankcard. 500 IN CNAME a.example.bankcard.",
          ";AUTHORITY",
          ";ADDITIONAL"
        ]
      }
    ]
  },
  {
    "Query": {
      "Name": "a.example.bankcard.",
      "Type": "SOA"
    },
    "Expected Response": [
      {
        "Server/s": "bind nsd ",
        "Response": [
          "id 12551",
          "opcode QUERY",
          "rcode NOERROR",
          "flags QR AA",
          ";QUESTION",
          "a.example.bankcard. IN SOA",
          ";ANSWER",
          "example.bankcard. 500 IN DNAME example.bankcard.",
          "a.example.bankcard. 500 IN CNAME a.example.bankcard.",
          ";AUTHORITY",
          ";ADDITIONAL"
        ]
      }
    ]
  },
  {
    "Query": {
      "Name": "a.example.bankcard.",
      "Type": "CNAME"
    },
    "Expected Response": [
      {
        "Server/s": "bind nsd ",
        "Response": [
          "id 54539",
          "opcode QUERY",
          "rcode NOERROR",
          "flags QR AA",
          ";QUESTION",
          "a.example.bankcard. IN CNAME",
          ";ANSWER",
          "example.bankcard. 500 IN DNAME example.bankcard.",
          "a.example.bankcard. 500 IN CNAME a.example.bankcard.",
          ";AUTHORITY",
          "bankcard. 500 IN NS ns1.outside.edu.",
          ";ADDITIONAL"
        ]
      }
    ]
  },
  {
    "Query": {
      "Name": "a.example.bankcard.",
      "Type": "DNAME"
    },
    "Expected Response": [
      {
        "Server/s": "bind nsd ",
        "Response": [
          "id 56798",
          "opcode QUERY",
          "rcode NOERROR",
          "flags QR AA",
          ";QUESTION",
          "a.example.bankcard. IN DNAME",
          ";ANSWER",
          "example.bankcard. 500 IN DNAME example.bankcard.",
          "a.example.bankcard. 500 IN CNAME a.example.bankcard.",
          ";AUTHORITY",
          ";ADDITIONAL"
        ]
      }
    ]
  },
  {
    "Query": {
      "Name": "a.example.bankcard.",
      "Type": "TXT"
    },
    "Expected Response": [
      {
        "Server/s": "bind nsd ",
        "Response": [
          "id 6752",
          "opcode QUERY",
          "rcode NOERROR",
          "flags QR AA",
          ";QUESTION",
          "a.example.bankcard. IN TXT",
          ";ANSWER",
          "example.bankcard. 500 IN DNAME example.bankcard.",
          "a.example.bankcard. 500 IN CNAME a.example.bankcard.",
          ";AUTHORITY",
          ";ADDITIONAL"
        ]
      }
    ]
  },
  {
    "Query": {
      "Name": "bankcard.",
      "Type": "A"
    },
    "Expected Response": [
      {
        "Server/s": "bind nsd ",
        "Response": [
          "id 6196",
          "opcode QUERY",
          "rcode NOERROR",
          "flags QR AA",
          ";QUESTION",
          "bankcard. IN A",
          ";ANSWER",
          ";AUTHORITY",
          "bankcard. 500 IN SOA ns1.outside.edu. root.campus.edu. 3 6048 86400 2419200 6048",
          ";ADDITIONAL"
        ]
      }
    ]
  },
  {
    "Query": {
      "Name": "bankcard.",
      "Type": "NS"
    },
    "Expected Response": [
      {
        "Server/s": "bind nsd ",
        "Response": [
          "id 20245",
          "opcode QUERY",
          "rcode NOERROR",
          "flags QR AA",
          ";QUESTION",
          "bankcard. IN NS",
          ";ANSWER",
          "bankcard. 500 IN NS ns1.outside.edu.",
          ";AUTHORITY",
          ";ADDITIONAL"
        ]
      }
    ]
  },
  {
    "Query": {
      "Name": "bankcard.",
      "Type": "SOA"
    },
    "Expected Response": [
      {
        "Server/s": "bind nsd ",
        "Response": [
          "id 63006",
          "opcode QUERY",
          "rcode NOERROR",
          "flags QR AA",
          ";QUESTION",
          "bankcard. IN SOA",
          ";ANSWER",
          "bankcard. 500 IN SOA ns1.outside.edu. root.campus.edu. 3 6048 86400 2419200 6048",
          ";AUTHORITY",
          "bankcard. 500 IN NS ns1.outside.edu.",
          ";ADDITIONAL"
        ]
      }
    ]
  },
  {
    "Query": {
      "Name": "bankcard.",
      "Type": "CNAME"
    },
    "Expected Response": [
      {
        "Server/s": "bind nsd ",
        "Response": [
          "id 65432",
          "opcode QUERY",
          "rcode NOERROR",
          "flags QR AA",
          ";QUESTION",
          "bankcard. IN CNAME",
          ";ANSWER",
          ";AUTHORITY",
          "bankcard. 500 IN SOA ns1.outside.edu. root.campus.edu. 3 6048 86400 2419200 6048",
          ";ADDITIONAL"
        ]
      }
    ]
  },
  {
    "Query": {
      "Name": "bankcard.",
      "Type": "DNAME"
    },
    "Expected Response": [
      {
        "Server/s": "bind nsd ",
        "Response": [
          "id 488",
          "opcode QUERY",
          "rcode NOERROR",
          "flags QR AA",
          ";QUESTION",
          "bankcard. IN DNAME",
          ";ANSWER",
          ";AUTHORITY",
          "bankcard. 500 IN SOA ns1.outside.edu. root.campus.edu. 3 6048 86400 2419200 6048",
          ";ADDITIONAL"
        ]
      }
    ]
  },
  {
    "Query": {
      "Name": "bankcard.",
      "Type": "TXT"
    },
    "Expected Response": [
      {
        "Server/s": "bind nsd ",
        "Response": [
          "id 42726",
          "opcode QUERY",
          "rcode NOERROR",
          "flags QR AA",
          ";QUESTION",
          "bankcard. IN TXT",
          ";ANSWER",
          ";AUTHORITY",
          "bankcard. 500 IN SOA ns1.outside.edu. root.campus.edu. 3 6048 86400 2419200 6048",
          ";ADDITIONAL"
        ]
      }
    ]
  },
  {
    "Query": {
      "Name": "a.bankcard.",
      "Type": "A"
    },
    "Expected Response": [
      {
        "Server/s": "bind nsd ",
        "Response": [
          "id 8384",
          "opcode QUERY",
          "rcode NXDOMAIN",
          "flags QR AA",
          ";QUESTION",
          "a.bankcard. IN A",
          ";ANSWER",
          ";AUTHORITY",
          "bankcard. 500 IN SOA ns1.outside.edu. root.campus.edu. 3 6048 86400 2419200 6048",
          ";ADDITIONAL"
        ]
      }
    ]
  },
  {
    "Query": {
      "Name": "a.bankcard.",
      "Type": "NS"
    },
    "Expected Response": [
      {
        "Server/s": "bind nsd ",
        "Response": [
          "id 25284",
          "opcode QUERY",
          "rcode NXDOMAIN",
          "flags QR AA",
          ";QUESTION",
          "a.bankcard. IN NS",
          ";ANSWER",
          ";AUTHORITY",
          "bankcard. 500 IN SOA ns1.outside.edu. root.campus.edu. 3 6048 86400 2419200 6048",
          ";ADDITIONAL"
        ]
      }
    ]
  },
  {
    "Query": {
      "Name": "a.bankcard.",
      "Type": "SOA"
    },
    "Expected Response": [
      {
        "Server/s": "bind nsd ",
        "Response": [
          "id 61838",
          "opcode QUERY",
          "rcode NXDOMAIN",
          "flags QR AA",
          ";QUESTION",
          "a.bankcard. IN SOA",
          ";ANSWER",
          ";AUTHORITY",
          "bankcard. 0 IN SOA ns1.outside.edu. root.campus.edu. 3 6048 86400 2419200 6048",
          ";ADDITIONAL"
        ]
      }
    ]
  },
  {
    "Query": {
      "Name": "a.bankcard.",
      "Type": "CNAME"
    },
    "Expected Response": [
      {
        "Server/s": "bind nsd ",
        "Response": [
          "id 844",
          "opcode QUERY",
          "rcode NXDOMAIN",
          "flags QR AA",
          ";QUESTION",
          "a.bankcard. IN CNAME",
          ";ANSWER",
          ";AUTHORITY",
          "bankcard. 500 IN SOA ns1.outside.edu. root.campus.edu. 3 6048 86400 2419200 6048",
          ";ADDITIONAL"
        ]
      }
    ]
  },
  {
    "Query": {
      "Name": "a.bankcard.",
      "Type": "DNAME"
    },
    "Expected Response": [
      {
        "Server/s": "bind nsd ",
        "Response": [
          "id 23532",
          "opcode QUERY",
          "rcode NXDOMAIN",
          "flags QR AA",
          ";QUESTION",
          "a.bankcard. IN DNAME",
          ";ANSWER",
          ";AUTHORITY",
          "bankcard. 500 IN SOA ns1.outside.edu. root.campus.edu. 3 6048 86400 2419200 6048",
          ";ADDITIONAL"
        ]
      }
    ]
  },
  {
    "Query": {
      "Name": "a.bankcard.",
      "Type": "TXT"
    },
    "Expected Response": [
      {
        "Server/s": "bind nsd ",
        "Response": [
          "id 63865",
          "opcode QUERY",
          "rcode NXDOMAIN",
          "flags QR AA",
          ";QUESTION",
          "a.bankcard. IN TXT",
          ";ANSWER",
          ";AUTHORITY",
          "bankcard. 500 IN SOA ns1.outside.edu. root.campus.edu. 3 6048 86400 2419200 6048",
          ";ADDITIONAL"
        ]
      }
    ]
  }
]