[
  {
    "Query": {
      "Name": "mybankcard.com.",
      "Type": "NS"
    },
    "Expected Response": [
      {
        "Server/s": "bind nsd knot powerdns ",
        "Response": [
          "id 27842",
          "opcode QUERY",
          "rcode NOERROR",
          "flags QR AA",
          ";QUESTION",
          "mybankcard.com. IN NS",
          ";ANSWER",
          "mybankcard.com. 500 IN NS bar.com.",
          "mybankcard.com. 500 IN NS com.",
          "mybankcard.com. 500 IN NS mybankcard.campus.",
          ";AUTHORITY",
          ";ADDITIONAL"
        ]
      }
    ],
    "ZenResponseTag": "E1"
  }
]