[
  {
    "Query": {
      "Name": "bankcard.fnni.email.",
      "Type": "TXT"
    },
    "Expected Response": [
      {
        "Server/s": "bind nsd knot powerdns ",
        "Response": [
          "id 56704",
          "opcode QUERY",
          "rcode NOERROR",
          "flags QR",
          ";QUESTION",
          "bankcard.fnni.email. IN TXT",
          ";ANSWER",
          ";AUTHORITY",
          "bankcard.fnni.email. 500 IN NS foo.email.",
          "bankcard.fnni.email. 500 IN NS bar.",
          "bankcard.fnni.email. 500 IN NS fnni.www.",
          ";ADDITIONAL"
        ]
      }
    ],
    "ZenResponseTag": "E4"
  }
]