[
  {
    "Query": {
      "Name": "email.uni.uni.bank.",
      "Type": "NS"
    },
    "Expected Response": [
      {
        "Server/s": "bind nsd knot powerdns ",
        "Response": [
          "id 64303",
          "opcode QUERY",
          "rcode NOERROR",
          "flags QR AA",
          ";QUESTION",
          "email.uni.uni.bank. IN NS",
          ";ANSWER",
          "email.uni.uni.bank. 500 IN NS www.uni.bank.",
          "email.uni.uni.bank. 500 IN NS bank.",
          "email.uni.uni.bank. 500 IN NS example.uni.bank.",
          ";AUTHORITY",
          ";ADDITIONAL"
        ]
      }
    ]
  }
]