[
  {
    "Query": {
      "Name": "foo.bank.bank.example.",
      "Type": "CNAME"
    },
    "Expected Response": [
      {
        "Server/s": "bind nsd knot powerdns ",
        "Response": [
          "id 10042",
          "opcode QUERY",
          "rcode NOERROR",
          "flags QR",
          ";QUESTION",
          "foo.bank.bank.example. IN CNAME",
          ";ANSWER",
          ";AUTHORITY",
          "foo.bank.bank.example. 500 IN NS email.bar.example.",
          ";ADDITIONAL"
        ]
      }
    ]
  }
]