[
  {
    "Query": {
      "Name": "email.bar.mybankcard.bankcard.",
      "Type": "SOA"
    },
    "Expected Response": [
      {
        "Server/s": "bind ",
        "Response": [
          "id 53237",
          "opcode QUERY",
          "rcode NOERROR",
          "flags QR",
          ";QUESTION",
          "email.bar.mybankcard.bankcard. IN SOA",
          ";ANSWER",
          ";AUTHORITY",
          "email.bar.mybankcard.bankcard. 500 IN NS bar.mybankcard.bankcard.",
          "email.bar.mybankcard.bankcard. 500 IN NS bar.*.bankcard.",
          ";ADDITIONAL"
        ]
      },
      {
        "Server/s": "nsd knot powerdns ",
        "Response": [
          "id 40856",
          "opcode QUERY",
          "rcode NOERROR",
          "flags QR",
          ";QUESTION",
          "email.bar.mybankcard.bankcard. IN SOA",
          ";ANSWER",
          ";AUTHORITY",
          "email.bar.mybankcard.bankcard. 500 IN NS bar.mybankcard.bankcard.",
          "email.bar.mybankcard.bankcard. 500 IN NS bar.*.bankcard.",
          ";ADDITIONAL",
          "bar.mybankcard.bankcard. 500 IN A 1.1.1.1"
        ]
      }
    ]
  }
]