[
  {
    "Query": {
      "Name": "www.bar.bar.example.",
      "Type": "AAAA"
    },
    "Expected Response": [
      {
        "Server/s": "bind nsd knot powerdns ",
        "Response": [
          "id 47884",
          "opcode QUERY",
          "rcode NOERROR",
          "flags QR",
          ";QUESTION",
          "www.bar.bar.example. IN AAAA",
          ";ANSWER",
          ";AUTHORITY",
          "www.bar.bar.example. 500 IN NS net.bar.example.",
          "www.bar.bar.example. 500 IN NS *.example.bar.example.",
          ";ADDITIONAL"
        ]
      }
    ]
  }
]