[
  {
    "Query": {
      "Name": "com.fnni.",
      "Type": "AAAA"
    },
    "Expected Response": [
      {
        "Server/s": "bind nsd knot powerdns ",
        "Response": [
          "id 48489",
          "opcode QUERY",
          "rcode NOERROR",
          "flags QR",
          ";QUESTION",
          "com.fnni. IN AAAA",
          ";ANSWER",
          ";AUTHORITY",
          "com.fnni. 500 IN NS com.net.com.fnni.",
          ";ADDITIONAL",
          "com.net.com.fnni. 500 IN A 1.1.1.1"
        ]
      }
    ]
  }
]