[
  {
    "Query": {
      "Name": "email.fnni.email.uni.",
      "Type": "NS"
    },
    "Expected Response": [
      {
        "Server/s": "bind nsd knot powerdns ",
        "Response": [
          "id 53290",
          "opcode QUERY",
          "rcode NOERROR",
          "flags QR AA",
          ";QUESTION",
          "email.fnni.email.uni. IN NS",
          ";ANSWER",
          "fnni.email.uni. 500 IN DNAME bankcard.foo.",
          "email.fnni.email.uni. 500 IN CNAME email.bankcard.foo.",
          ";AUTHORITY",
          ";ADDITIONAL"
        ]
      }
    ]
  }
]