[
  {
    "Query": {
      "Name": "mybankcard.fnni.email.",
      "Type": "NS"
    },
    "Expected Response": [
      {
        "Server/s": "bind nsd knot powerdns ",
        "Response": [
          "id 36032",
          "opcode QUERY",
          "rcode NOERROR",
          "flags QR AA",
          ";QUESTION",
          "mybankcard.fnni.email. IN NS",
          ";ANSWER",
          "mybankcard.fnni.email. 500 IN NS fnni.",
          "mybankcard.fnni.email. 500 IN NS mybankcard.bankcard.email.",
          "mybankcard.fnni.email. 500 IN NS bar.",
          ";AUTHORITY",
          ";ADDITIONAL"
        ]
      }
    ]
  }
]